EduDesignGen/__init__.py
EduDesignGen/core.py
EduDesignGen-0.1.1.dist-info/METADATA
EduDesignGen-0.1.1.dist-info/WHEEL
EduDesignGen-0.1.1.dist-info/top_level.txt
EduDesignGen-0.1.1.dist-info/RECORD
